odoo10_addon_auto_backup-10.0.1.0.2-py2.7-nspkg.pth
odoo10_addon_auto_backup-10.0.1.0.2.dist-info/top_level.txt
odoo10_addon_auto_backup-10.0.1.0.2.dist-info/WHEEL
odoo10_addon_auto_backup-10.0.1.0.2.dist-info/RECORD
odoo10_addon_auto_backup-10.0.1.0.2.dist-info/metadata.json
odoo10_addon_auto_backup-10.0.1.0.2.dist-info/DESCRIPTION.rst
odoo10_addon_auto_backup-10.0.1.0.2.dist-info/METADATA
odoo10_addon_auto_backup-10.0.1.0.2.dist-info/namespace_packages.txt
odoo/addons/auto_backup/__manifest__.py
odoo/addons/auto_backup/__init__.py
odoo/addons/auto_backup/README.rst
odoo/addons/auto_backup/security/ir.model.access.csv
odoo/addons/auto_backup/view/db_backup_view.xml
odoo/addons/auto_backup/models/db_backup.py
odoo/addons/auto_backup/models/__init__.py
odoo/addons/auto_backup/i18n/ja.po
odoo/addons/auto_backup/i18n/lv.po
odoo/addons/auto_backup/i18n/zh_CN.po
odoo/addons/auto_backup/i18n/nb_NO.po
odoo/addons/auto_backup/i18n/uk.po
odoo/addons/auto_backup/i18n/es_AR.po
odoo/addons/auto_backup/i18n/ko.po
odoo/addons/auto_backup/i18n/tr_TR.po
odoo/addons/auto_backup/i18n/ru.po
odoo/addons/auto_backup/i18n/gl_ES.po
odoo/addons/auto_backup/i18n/pt.po
odoo/addons/auto_backup/i18n/fr_CH.po
odoo/addons/auto_backup/i18n/it.po
odoo/addons/auto_backup/i18n/es_CL.po
odoo/addons/auto_backup/i18n/es.po
odoo/addons/auto_backup/i18n/nl_BE.po
odoo/addons/auto_backup/i18n/ar.po
odoo/addons/auto_backup/i18n/lt.po
odoo/addons/auto_backup/i18n/vi_VN.po
odoo/addons/auto_backup/i18n/ro.po
odoo/addons/auto_backup/i18n/tr.po
odoo/addons/auto_backup/i18n/sr.po
odoo/addons/auto_backup/i18n/es_PY.po
odoo/addons/auto_backup/i18n/mk.po
odoo/addons/auto_backup/i18n/hr.po
odoo/addons/auto_backup/i18n/bg.po
odoo/addons/auto_backup/i18n/es_EC.po
odoo/addons/auto_backup/i18n/zh_TW.po
odoo/addons/auto_backup/i18n/hu.po
odoo/addons/auto_backup/i18n/fr_CA.po
odoo/addons/auto_backup/i18n/gl.po
odoo/addons/auto_backup/i18n/lt_LT.po
odoo/addons/auto_backup/i18n/ca.po
odoo/addons/auto_backup/i18n/id.po
odoo/addons/auto_backup/i18n/es_CR.po
odoo/addons/auto_backup/i18n/he.po
odoo/addons/auto_backup/i18n/es_CO.po
odoo/addons/auto_backup/i18n/sl.po
odoo/addons/auto_backup/i18n/sr@latin.po
odoo/addons/auto_backup/i18n/th.po
odoo/addons/auto_backup/i18n/es_PE.po
odoo/addons/auto_backup/i18n/es_ES.po
odoo/addons/auto_backup/i18n/cs.po
