Metadata-Version: 2.0
Name: odoo10-addon-auto-backup
Version: 10.0.1.0.2
Summary: Backups database
Home-page: http://www.vanroey.be/applications/bedrijfsbeheer/odoo
Author: Yenthe Van Ginneken, Agile Business Group, Grupo ESOC Ingeniería de Servicios, LasLabs, Odoo Community Association (OCA)
Author-email: support@odoo-community.org
License: AGPL-3
Platform: UNKNOWN
Requires-Dist: odoo (<10.1dev,>=10.0)
Requires-Dist: pysftp
Classifier: Programming Language :: Python :: 2.7
Classifier: Framework :: Odoo
Classifier: License :: OSI Approved :: GNU Affero General Public License v3
